vgmusic/__init__.py
vgmusic/cli.py
vgmusic/rest.py
vgmusic/vgmusic.py
vgmusic-1.0.2.dist-info/entry_points.txt
vgmusic-1.0.2.dist-info/LICENSE
vgmusic-1.0.2.dist-info/WHEEL
vgmusic-1.0.2.dist-info/METADATA
vgmusic-1.0.2.dist-info/RECORD
