Metadata-Version: 2.1
Name: vgmusic
Version: 1.0.2
Summary: Unofficial Python API for vgmusic.com.
Home-page: https://github.com/ongyx/vgmusic.py
Author: Ong Yong Xin
Author-email: ongyongxin2020+github@gmail.com
Requires-Python: >=3.6
Classifier: Programming Language :: Python :: 3
Classifier: License :: OSI Approved :: MIT License
Classifier: Operating System :: OS Independent
Requires-Dist: beautifulsoup4>=4.9.1
Requires-Dist: html5lib>=1.1
Requires-Dist: requests>=2.24.0
Requires-Dist: click>=7.1.2 ; extra == "cli"
Requires-Dist: pydoc-markdown>=3.10.1 ; extra == "doc"
Requires-Dist: fastapi>=0.63.0 ; extra == "rest"
Requires-Dist: uvicorn[standard]>=0.13.3 ; extra == "rest"
Provides-Extra: cli
Provides-Extra: doc
Provides-Extra: rest
